fuelpricesqld/__init__.py
fuelpricesqld/api/__init__.py
fuelpricesqld/api/client.py
fuelpricesqld/database/__init__.py
fuelpricesqld/database/models/__init__.py
fuelpricesqld/database/models/base.py
fuelpricesqld/database/models/brand.py
fuelpricesqld/database/models/country.py
fuelpricesqld/database/models/fuels.py
fuelpricesqld/database/models/prices.py
fuelpricesqld/database/models/regions.py
fuelpricesqld/database/models/sites.py
fuelpricesqld/database/session.py
fuelpricesqld/etls/__init__.py
fuelpricesqld/etls/etls.py
fuelpricesqld-0.1.0.dev1.dist-info/LICENSE
fuelpricesqld-0.1.0.dev1.dist-info/METADATA
fuelpricesqld-0.1.0.dev1.dist-info/WHEEL
fuelpricesqld-0.1.0.dev1.dist-info/RECORD
