Metadata-Version: 2.3
Name: fuelpricesqld
Version: 0.1.0.dev1
Summary: 
Author: Your Name
Author-email: you@example.com
Requires-Python: >=3.10
Classifier: Programming Language :: Python :: 3
Classifier: Programming Language :: Python :: 3.10
Classifier: Programming Language :: Python :: 3.11
Classifier: Programming Language :: Python :: 3.12
Classifier: Programming Language :: Python :: 3.13
Requires-Dist: geoalchemy2 (>=0.17.1,<0.18.0)
Requires-Dist: polars (>=1.30.0,<2.0.0)
Requires-Dist: requests (>=2.32.3,<3.0.0)
Requires-Dist: sqlalchemy (>=2.0.41,<3.0.0)
